mokuwiki.py
mokuwiki-1.0.1.dist-info/LICENSE.txt
mokuwiki-1.0.1.dist-info/METADATA
mokuwiki-1.0.1.dist-info/WHEEL
mokuwiki-1.0.1.dist-info/entry_points.txt
mokuwiki-1.0.1.dist-info/top_level.txt
mokuwiki-1.0.1.dist-info/RECORD
