Metadata-Version: 2.1
Name: mokuwiki
Version: 1.0.1
Summary: Convert a folder of Markdown documents, replacing inter-page link and tag markup with Markdown links and lists
Home-page: https://github.com/encodis/mokuwiki
Author: Philip Hodder
Author-email: philip.hodder@encodis.com
License: MIT
Keywords: markdown wiki converter
Platform: UNKNOWN
Classifier: Intended Audience :: Developers
Classifier: License :: OSI Approved :: MIT License
Classifier: Programming Language :: Python
Classifier: Topic :: Text Processing :: Markup
Classifier: Topic :: Utilities
Requires-Dist: pyyaml (>=5.1)
